go_gae_proxy
