Metadata-Version: 1.1
Name: go-proxy-client
Version: 0.2
Summary: Handler for urllib2 to use a go-proxy instance as proxy server
Home-page: UNKNOWN
Author: Stefan Richter
Author-email: stefan@02strich.de
License: UNKNOWN
Platform: UNKNOWN
Classifier: License :: OSI Approved :: MIT License
Classifier: Operating System :: OS Independent
Classifier: Programming Language :: Python
Classifier: Programming Language :: Python :: 2
Classifier: Programming Language :: Python :: 2.4
Classifier: Programming Language :: Python :: 2.5
Classifier: Programming Language :: Python :: 2.6
Classifier: Programming Language :: Python :: 2.7
Classifier: Programming Language :: Python :: 3
Classifier: Programming Language :: Python :: 3.1
